Workbook

Sheet Tableau de Bord
A1: Tableau de Bord — Comptabilité Fournisseur
A2: Vue consolidée de toutes les opérations commerciales
A3: N° | B3: Activité | C3: Capital Disponible | D3: Capital Investi | E3: Capital en Caisse | F3: Chiffre d'Affaires | G3: Bénéfice Net | H3: Marge Nette
A4: 1 | B4: Op. Poisson Séché | C4: ='Op. Poisson Séché'!B3 | D4: ='Op. Poisson Séché'!B4 | E4: ='Op. Poisson Séché'!B5 | F4: ='Op. Poisson Séché'!B9 | G4: ='Op. Poisson Séché'!B8 | H4: ='Op. Poisson Séché'!B10
A5: 2 | B5: Op. Agro-alimentaire | C5: ='Op. Agro-alimentaire'!B13 | D5: ='Op. Agro-alimentaire'!B14 | E5: ='Op. Agro-alimentaire'!B15 | F5: ='Op. Agro-alimentaire'!H10 | G5: ='Op. Agro-alimentaire'!I10 | H5: ='Op. Agro-alimentaire'!J10
B6: TOTAL | C6: =SUM(C4:C5) | D6: =SUM(D4:D5) | E6: =SUM(E4:E5) | F6: =SUM(F4:F5) | G6: =SUM(G4:G5) | H6: =G6/F6
A8: Pour ajouter une opération : créer une nouvelle feuille et ajouter une ligne dans ce tableau.

Sheet Op. Poisson Séché
A1: Opération — Poisson Séché
A2: Désignation | B2: Montant
A3: Capital Disponible | B3: 200000
A4: Capital Investi | B4: 150000
A5: Capital en Caisse (non investi) | B5: =B3-B4
A6: Vente 1 — Bénéfice réalisé | B6: 35000
A7: Vente 2 — Bénéfice réalisé | B7: 48000
A8: Bénéfice Net Total | B8: =B6+B7
A9: Chiffre d'Affaires | B9: =B4+B8
A10: Marge Nette | B10: =B8/B4

Sheet Op. Agro-alimentaire
A1: Opération — Agro-alimentaire
A2: Capital Disponible : 500 000 F | Capital Investi : 173 850 F | Capital en Caisse : 326 150 F
A3: Produit | B3: Variété | C3: Qté | D3: Unité | E3: Prix Achat | F3: Coût Achat | G3: Prix Vente | H3: Chiffre d'Affaires | I3: Bénéfice | J3: Marge
A4: Tomates | B4: Cobra | C4: 8 | D4: Caisse | E4: 7000 | F4: =C4*E4 | G4: 11000 | H4: =C4*G4 | I4: =H4-F4 | J4: =I4/H4
A5: Tomates | B5: Ndiamb | C5: 4 | D5: Caisse | E5: 5000 | F5: =C5*E5 | G5: 9000 | H5: =C5*G5 | I5: =H5-F5 | J5: =I5/H5
A6: Piment | B6: Sofia | C6: 28 | D6: kg | E6: 800 | F6: =C6*E6 | G6: 1500 | H6: =C6*G6 | I6: =H6-F6 | J6: =I6/H6
A7: Piment | B7: Jukuli | C7: 24 | D7: kg | E7: 800 | F7: =C7*E7 | G7: 1500 | H7: =C7*G7 | I7: =H7-F7 | J7: =I7/H7
A8: Kaani Salaat | B8: — | C8: 50 | D8: kg | E8: 325 | F8: =C8*E8 | G8: 500 | H8: =C8*G8 | I8: =H8-F8 | J8: =I8/H8
A9: Transport | F9: 40000
A10: TOTAL | F10: =SUM(F4:F8)+F9 | H10: =SUM(H4:H8) | I10: =H10-F10 | J10: =I10/H10
A12: BILAN DE L'OPÉRATION
A13: Capital Disponible | B13: 500000
A14: Capital Investi | B14: =F10
A15: Capital en Caisse | B15: =B13-B14
A16: Chiffre d'Affaires | B16: =H10
A17: Bénéfice Net | B17: =I10
A18: Marge Nette | B18: =J10
